LICENSE
MANIFEST.in
README.rst
setup.py
consider/__init__.py
consider/consider.py
consider.egg-info/PKG-INFO
consider.egg-info/SOURCES.txt
consider.egg-info/dependency_links.txt
consider.egg-info/top_level.txt