Metadata-Version: 1.0
Name: consider
Version: 0.1.1
Summary: Consider is a parser for the ThinkGear protocol used by NeuroSky devices.
Home-page: https://github.com/lanius/consider/
Author: lanius
Author-email: lanius@nirvake.org
License: MIT
Platform: UNKNOWN
Classifier: Development Status :: 4 - Beta
Classifier: Intended Audience :: Developers
Classifier: License :: OSI Approved :: MIT License
Classifier: Operating System :: OS Independent
Classifier: Programming Language :: Python
Classifier: Topic :: Software Development :: Libraries :: Python Modules
